{"airship":{"bgm":{"name":"Ship3","pan":0,"pitch":100,"volume":90},"characterIndex":3,"characterName":"Vehicle","startMapId":0,"startX":0,"startY":0},"armorTypes":["","一般防具","魔法防具","軽装防具","重装防具","小型盾","大型盾"],"attackMotions":[{"type":0,"weaponImageId":0},{"type":1,"weaponImageId":1},{"type":1,"weaponImageId":2},{"type":1,"weaponImageId":3},{"type":1,"weaponImageId":4},{"type":1,"weaponImageId":5},{"type":1,"weaponImageId":6},{"type":2,"weaponImageId":7},{"type":2,"weaponImageId":8},{"type":2,"weaponImageId":9},{"type":0,"weaponImageId":10},{"type":0,"weaponImageId":11},{"type":0,"weaponImageId":12}],"battleBgm":{"name":"Battle1","pan":0,"pitch":100,"volume":90},"battleback1Name":"Cobblestones3","battleback2Name":"","battlerHue":0,"battlerName":"Dragon","boat":{"bgm":{"name":"Ship1","pan":0,"pitch":100,"volume":90},"characterIndex":0,"characterName":"Vehicle","startMapId":0,"startX":0,"startY":0},"currencyUnit":"Ｇ","defeatMe":{"name":"","pan":0,"pitch":100,"volume":90},"editMapId":56,"elements":["","物理","炎","氷","雷","水","土","風","光","闇"],"equipTypes":["","武器","身体","頭","身体","装飾品"],"gameTitle":"アルフィミアの塔","gameoverMe":{"name":"Gameover1","pan":0,"pitch":100,"volume":90},"locale":"ja_JP","magicSkills":[1],"menuCommands":[true,true,true,true,false,true],"optDisplayTp":true,"optDrawTitle":true,"optExtraExp":false,"optFloorDeath":false,"optFollowers":true,"optSideView":false,"optSlipDeath":false,"optTransparent":true,"partyMembers":[1],"ship":{"bgm":{"name":"Ship2","pan":0,"pitch":100,"volume":90},"characterIndex":1,"characterName":"Vehicle","startMapId":0,"startX":0,"startY":0},"skillTypes":["","スキル","必殺技","炎の魔剣","氷の魔剣","雷の魔剣","風の魔剣","光の魔剣","闇の魔剣","雷炎の魔剣","氷風の魔剣","黒雷炎の魔剣","白氷風の魔剣",""],"sounds":[{"name":"Cursor2","pan":0,"pitch":100,"volume":45},{"name":"Decision1","pan":0,"pitch":100,"volume":45},{"name":"Cancel2","pan":0,"pitch":100,"volume":45},{"name":"Buzzer1","pan":0,"pitch":100,"volume":45},{"name":"Equip1","pan":0,"pitch":100,"volume":55},{"name":"Save","pan":0,"pitch":100,"volume":90},{"name":"Load","pan":0,"pitch":100,"volume":90},{"name":"Battle1","pan":0,"pitch":100,"volume":50},{"name":"Run","pan":0,"pitch":100,"volume":90},{"name":"Attack3","pan":0,"pitch":100,"volume":90},{"name":"Damage4","pan":0,"pitch":100,"volume":90},{"name":"Collapse1","pan":0,"pitch":100,"volume":50},{"name":"Collapse2","pan":0,"pitch":100,"volume":50},{"name":"Collapse3","pan":0,"pitch":100,"volume":55},{"name":"Damage5","pan":0,"pitch":100,"volume":90},{"name":"Collapse4","pan":0,"pitch":100,"volume":90},{"name":"Recovery","pan":0,"pitch":100,"volume":90},{"name":"Miss","pan":0,"pitch":100,"volume":90},{"name":"Evasion1","pan":0,"pitch":100,"volume":90},{"name":"Evasion2","pan":0,"pitch":100,"volume":90},{"name":"Reflection","pan":0,"pitch":100,"volume":90},{"name":"Shop1","pan":0,"pitch":100,"volume":90},{"name":"Item3","pan":0,"pitch":100,"volume":90},{"name":"Item3","pan":0,"pitch":100,"volume":90}],"startMapId":91,"startX":15,"startY":9,"switches":["","サキュバス透明化","","","","","","","","","可憐戦勝利","","","","","","","","","","","オープニング","可憐戦敗北","可憐戦終了","可憐戦勝利ノーマル","可憐戦勝利バッド","小悪魔勝利","淫気封印解除","淫気の説明","アルの疑惑","ボス勝利","初めての店員さん","助けを呼ぶ声","モンスターの仕組み","優香登場","優香に敗北","優香に勝利","優香に勝利グッド","優香に勝利ノーマル","優香に勝利バッド","可憐に敗北","小悪魔簡易化","店員(1)簡易化","小悪魔B簡簡易化","ロリダークエルフ簡易化","店員(2)簡易化","店員（3）簡易化","店員（4）簡易化","店員（5）簡易化","盗賊サキュバス簡易化","ドライアド簡易化","店員（6）簡易化","マジックサキュバス簡易化","","","","","","","","","可憐TP20","可憐TP40","可憐TP60","可憐TP80","2TP20","2TP40","2TP60","2TP80","3TP80","4TP80","5TP80","ダークエルフ生かされ","ダークエルフ生かされ2","TP50","2TP50","3TP50","4TP50","5TP50","","","可憐に敗北2連敗","可憐にリベンジされた","優香イベント消去用スイッチ","可憐2戦目終了","奢るよ！","奢られるよ！","宿屋でボス戦の疲れをとろう","100Gの部屋","1000Gの部屋","一晩目","食べた！","お開き！","南通り","ショップ","コロシアム","雑貨屋","家事の","酒場","1割利子借りた","借りた","借りなかった","凛を犯さない","凛に勝利","凛にリベンジ","凛に敗北","お嬢様消去","高木優香コロシアム","優香に敗北","姫野光コロシアム","六花に敗北","六花を犯した","六花に勝利","凛→お医者","お金を返した","六花に2連敗","敗北後六花に勝利","六花解放の条件","恭子を奴隷にする","優香に勝利","助けよう","奴隷に使用","恭子と試合","恭子に勝利","恭子を犯した","宝箱","犯した女の子に犯された","2戦目可憐を犯した","2戦目可憐に勝利","3戦目可憐に勝利","3戦目可憐を犯した","優香にミストを取られた","難易度ノーマル","難易度イージー","キス優香イベント戦終了","宝箱１","宝箱２","宝箱３","小悪魔A自動化","小悪魔B自動化","ロリダークエルフ自動化","体験版負け１","体験版負け２","体験版負け３","2層の装備品","バニー店員簡易化１","バニー店員簡易化２","バニー店員簡易化３","バニー店員簡易化４","バニー店員簡易化５","バニー店員簡易化６","盗賊サキュバス自動化","1－2回想","1-1回想","ダークエルフに勝利","1-3回想","優香戦カウントダウン","優香変身","武器をもらった","防具をもらった","武器を借りた","メタられた","","遠見可憐1戦目終了","頑張るスイッチ","クリスタル１","クリスタル２","クリスタル３","クリスタル４","アップルパイ出現","2層クリスタル１","2層クリスタル２","ダークエルフ登場","女神登場","3層クリスタル","4層1ショップ","4層2ショップ","4層3ショップ","4層4ショップ","アルのことを認識できるの？","あの幻術は真実なの？","なぜ自分たちにあんな幻術を？","この先にいるのはある？","天使出現１","天使出現２","天使出現３","女神出現２","木が邪魔","試合中","凛を犯した","優香を犯した","六花を犯した","恭子を犯した","エンカウントoff","盗賊サキュバス自動化","ドライアド自動化","マジックサキュバス簡易","1試合目賞金","2試合目賞金","3試合目賞金","戦闘をスキップ","マーシャにイかされた","恭子イベントエンド","桃香（足りない）","条件桃香断った","桃香とろとろ射精","桃香貢ぎマゾ射精","誘い条件桃香断った","ショップまで飛んだ","おっぱいマゾ","明日まで待ってね","明日まで待ったよ","アリサ消去","グラスファ入手","2回目消去","襲撃勝利","優香を説得","森で優香を犯した","優香B","優香C","優香D","メイドサキュバスAに勝った","聖剣が気になるアル","3戦目可憐に敗北した","優香戦グラスファ装備","メイドサキュバスAに負けた","メイドB見張り","可憐見張り","メイド可憐に負けた","メイド長に負けた","メイドサキュバスAの家畜","メイドAドレイン1","自由時間！","メイドAドレイン2","形を持たぬ者簡易化","形を持たぬ者自動化","メイドサキュバスBの家畜","めいどBドレイン1","めいどBドレイン2","メイドｂに負けた","1盤あるB","脱走後おｎ","メイド可憐の家畜","可憐ドレイン1","可憐ドレイン2","ミズキの説明","メイドB脱走","脱走","脱走アナウンス","サキュバス可憐に勝利","六花の仕返し","六花解放","可憐足奴隷","2-1回想","2-2回想","2-3回想","街回想","可憐リセット","可憐3千終了","3千可憐消去","優香と協力","優香の提案拒否","家畜でいい","脱走準備！！","1回目脱走","食堂発見","魅了チュートリアル","魔法剣チュートリアル","優香を犯したことをなかったことに","闘技場で優香を犯した","ご主人様B線","ご主人様A線","台所発見","廊下発見","休憩室発見","会議室発見","ピアノ室発見","図書室発見","ショップ発見","2階ピアノ室発見","カジノ発見","バー発見","部屋発見","メイド長に取り押さえられた","メイド長に勝利","サキュバスクイーンに勝利","サキュバス優香に勝利","優香反省","優香嘔吐","優香にとってゲーム","準備してくる","階層主の復活","侵入","優香と協力2","優香と協力3","ハード","ナイトメア","メイドスキップ説明","宝箱譲った","","","大淫魔自動化","アイドルサキュバス","神官サキュバス自動化","セーレ自動化","大淫魔簡易化","アイドル簡易化","神官サキュバス簡易化","セーレ簡易化","ダンタリオン勝利","4層ダンタリオン","4層アル","サキュバス透明か","フレイに勝利","4-1魔法陣","4-2魔法陣","4-3魔法陣","4-4魔法陣","3-1海藻","3-1修道院階層","広場階層","3-3海藻","3-2海藻","4-1海藻","4-2海藻","4-3海藻","4-4海藻","ダンタリオン海藻","アル階層","4-2ファスト","4-3ファスト","4-4ファスト","アルを殺した","マーシャ断った","店員会話1","店員会話2","店員会話3","店員会話4","料理","女将会話1","女将会話2","女将会話3","女将会話4","マーシャ誘惑","桃香部屋","カジノでイかされた","奴隷会話","女将料理1","女将料理２","女将料理３","女将料理4","桃香2回目","","","","","","","","","","","","","","","","","","","","","","","","","","","","","","","","","","","","","","","","","","","","","","","","","ショップ"],"terms":{"basic":["レベル","Lv","ＨＰ","HP","ＭＰ","MP","興奮度","興奮度","経験値","EXP"],"commands":["戦う","逃げる","攻撃","防御","アイテム","スキル","装備","ステータス","並び替え","セーブ","ゲーム終了","オプション","武器","防具","大事なもの","装備","最強装備","全て外す","ニューゲーム","コンティニュー",null,"タイトルへ","やめる",null,"購入する","売却する"],"params":["最大ＨＰ","最大ＭＰ","攻撃力","防御力","魔法力","魔法防御","敏捷性","運","命中率","回避率"],"messages":{"actionFailure":"%1には効かなかった！","actorDamage":"%1は %2 のダメージを受けた！","actorDrain":"%1は%2を %3 奪われた！","actorGain":"%1の%2が %3 増えた！","actorLoss":"%1の%2が %3 減った！","actorNoDamage":"%1はダメージを受けていない！","actorNoHit":"ミス！　%1はダメージを受けていない！","actorRecovery":"%1の%2が %3 回復した！","alwaysDash":"常時ダッシュ","bgmVolume":"BGM 音量","bgsVolume":"BGS 音量","buffAdd":"%1の%2が上がった！","buffRemove":"%1の%2が元に戻った！","commandRemember":"コマンド記憶","counterAttack":"%1の反撃！","criticalToActor":"痛恨の一撃！！","criticalToEnemy":"会心の一撃！！","debuffAdd":"%1の%2が下がった！","defeat":"%1は戦いに敗れた。","emerge":"%1が出現！","enemyDamage":"%1に %2 のダメージを与えた！","enemyDrain":"%1の%2を %3 奪った！","enemyGain":"%1の%2が %3 増えた！","enemyLoss":"%1の%2が %3 減った！","enemyNoDamage":"%1にダメージを与えられない！","enemyNoHit":"ミス！　%1にダメージを与えられない！","enemyRecovery":"%1の%2が %3 回復した！","escapeFailure":"しかし逃げることはできなかった！","escapeStart":"%1は逃げ出した！","evasion":"%1は攻撃をかわした！","expNext":"次の%1まで","expTotal":"現在の%1","file":"ファイル","levelUp":"%1は%2 %3 に上がった！","loadMessage":"どのファイルをロードしますか？","magicEvasion":"%1は魔法を打ち消した！","magicReflection":"%1は魔法を跳ね返した！","meVolume":"ME 音量","obtainExp":"%1 の%2を獲得！","obtainGold":"お金を %1\\G 手に入れた！","obtainItem":"%1を手に入れた！","obtainSkill":"%1を覚えた！","partyName":"%1たち","possession":"持っている数","preemptive":"%1は先手を取った！","saveMessage":"どのファイルにセーブしますか？","seVolume":"SE 音量","substitute":"%1が%2をかばった！","surprise":"%1は不意をつかれた！","useItem":"%1は%2を使った！","victory":"%1の勝利！"}},"testBattlers":[{"actorId":1,"equips":[8,9,49,50,16],"level":50},{"actorId":0,"equips":[2,1,2,3,0],"level":1},{"actorId":0,"equips":[3,0,2,3,4],"level":1},{"actorId":0,"equips":[4,0,2,3,4],"level":1}],"testTroopId":105,"title1Name":"Tower1","title2Name":"","titleBgm":{"name":"テーマ","pan":0,"pitch":100,"volume":45},"variables":["","","","","","ドレイン前レベル","ドレイン後レベル1","ドレイン後レベル2","ドレイン後レベル3","","レベルドレイン簡易化1","戦闘中興奮度","魔法剣参照レベル","魔法剣参照MP","限界魔力成功率","レベルドレイン数値","アルの-好感度","現在MP","PvPレベルドレイン前","PvPレベルドレイン後","ドレイン経験値","雷","MP","回想レベル","回想後レベル","寸止め回数","寸止め回数","ドレイン前金額","ドレイン後金額","ドレイン経験値量","ドレイン前本金額","１ドレイン後金額","計算用金額","計算用金額2","とろとろ射精回数","計算用総資産","始まる経験値","終わる経験値","計算経験値","計算経験値2","計算経験値3","六花確率","回想計算","回想レベル調整","興奮度チュートリアル","現在体力","現在MP","変身前体力","変身後体力","レベル32経験値","類型経験値","料理","食べた回数","敵HP","敵攻撃力","敵防御力","敵素早さ","回想ドレイン","","",""],"versionId":56816309,"victoryMe":{"name":"Victory1","pan":0,"pitch":100,"volume":50},"weaponTypes":["","短剣","剣","フレイル","斧","ムチ","杖","弓","クロスボウ","銃","爪","グローブ","槍"],"windowTone":[0,0,0,0],"hasEncryptedImages":true,"hasEncryptedAudio":true,"encryptionKey":"7d89d405b100197f0e967c0f8d03fb00"}